{
	"id": "f5434ee0-5225-4134-82e6-bea1d1cdbaca",
	"name": "project1",
	"values": [
		{
			"key": "base_url",
			"value": "https://restful-booker.herokuapp.com",
			"type": "default",
			"enabled": true
		},
		{
			"key": "id",
			"value": "",
			"type": "any",
			"enabled": true
		},
		{
			"key": "newToken",
			"value": "",
			"type": "any",
			"enabled": true
		},
		{
			"key": "path",
			"value": "booking",
			"type": "default",
			"enabled": true
		}
	],
	"_postman_variable_scope": "environment",
	"_postman_exported_at": "2022-07-05T22:09:10.642Z",
	"_postman_exported_using": "Postman/9.23.3"
}